func_adl_xAOD/__init__.py
func_adl_xAOD/use_exe_servicex.py
func_adl_xAOD/util_LINQ.py
func_adl_xAOD/backend/__init__.py
func_adl_xAOD/backend/R21Code/ATestRun_eljob.py
func_adl_xAOD/backend/R21Code/README.md
func_adl_xAOD/backend/R21Code/package_CMakeLists.txt
func_adl_xAOD/backend/R21Code/query.cxx
func_adl_xAOD/backend/R21Code/query.h
func_adl_xAOD/backend/R21Code/runner.sh
func_adl_xAOD/backend/cpplib/__init__.py
func_adl_xAOD/backend/cpplib/cpp_ast.py
func_adl_xAOD/backend/cpplib/cpp_functions.py
func_adl_xAOD/backend/cpplib/cpp_representation.py
func_adl_xAOD/backend/cpplib/cpp_types.py
func_adl_xAOD/backend/cpplib/cpp_vars.py
func_adl_xAOD/backend/cpplib/math_utils.py
func_adl_xAOD/backend/dataset_resolvers/__init__.py
func_adl_xAOD/backend/dataset_resolvers/gridds.py
func_adl_xAOD/backend/xAODlib/EventCollections.py
func_adl_xAOD/backend/xAODlib/Jets.py
func_adl_xAOD/backend/xAODlib/__init__.py
func_adl_xAOD/backend/xAODlib/ast_to_cpp_translator.py
func_adl_xAOD/backend/xAODlib/atlas_xaod_executor.py
func_adl_xAOD/backend/xAODlib/exe_atlas_xaod_docker.py
func_adl_xAOD/backend/xAODlib/exe_atlas_xaod_hash_cache.py
func_adl_xAOD/backend/xAODlib/generated_code.py
func_adl_xAOD/backend/xAODlib/result_handlers.py
func_adl_xAOD/backend/xAODlib/statement.py
func_adl_xAOD/backend/xAODlib/util_scope.py
func_adl_xAOD.backend-1.0.0.dist-info/METADATA
func_adl_xAOD.backend-1.0.0.dist-info/WHEEL
func_adl_xAOD.backend-1.0.0.dist-info/top_level.txt
func_adl_xAOD.backend-1.0.0.dist-info/RECORD
