Metadata-Version: 2.1
Name: func-adl-xAOD.backend
Version: 1.0.0
Summary: Backend to generate and run C++ files for Functional Analysis Description Language for accessing ATLAS xAOD files.
Home-page: https://github.com/iris-hep/func_adl_xAOD
Author: G. Watts (IRIS-HEP/UW Seattle)
Author-email: gwatts@uw.edu
Maintainer: Gordon Watts (IRIS-HEP/UW Seattle)
Maintainer-email: gwatts@uw.edu
License: TBD
Platform: Any
Classifier: Development Status :: 3 - Alpha
Classifier: Intended Audience :: Developers
Classifier: Intended Audience :: Information Technology
Classifier: Programming Language :: Python
Classifier: Programming Language :: Python :: 3.7
Classifier: Topic :: Software Development
Classifier: Topic :: Utilities
Requires-Python: >=3.7, <3.8
Requires-Dist: jinja2
Requires-Dist: func-adl-xAOD (==1.0.0)
